multiplier_fsm.v
module multiplier_fsm(
    input  clk,
    input  reset,
    input  start,
    input  lsb,

    output reg load,
    output reg add,
    output reg shift,
    output reg done
);

reg [5:0] count;
reg [1:0] state;

localparam IDLE  = 2'b00;
localparam CHECK = 2'b01;
localparam ADD   = 2'b10;
localparam SHIFT = 2'b11;

always @(posedge clk or posedge reset) begin
    if (reset) begin
        state <= IDLE;
        count <= 6'd0;
        load  <= 1'b0;
        add   <= 1'b0;
        shift <= 1'b0;
        done  <= 1'b0;
    end else begin
        // limpiar pulsos
        load  <= 1'b0;
        add   <= 1'b0;
        shift <= 1'b0;
        done  <= 1'b0;

        case (state)
        IDLE: begin
            if (start) begin
                load  <= 1'b1;   // carga {A=0, Q=b} y M=a
                count <= 6'd0;
                state <= CHECK;
            end
        end

        CHECK: begin
            if (lsb)
                state <= ADD;    // si Q0=1 → sumar
            else
                state <= SHIFT;  // si Q0=0 → ir directo a shift
        end

        ADD: begin
            add   <= 1'b1;       // A = A + M
            state <= SHIFT;      // luego desplazar
        end

        SHIFT: begin
            shift <= 1'b1;       // {A,Q} >> 1
            count <= count + 1'b1;
            if (count == 6'd31) begin
                state <= IDLE;
                done <= 1'b1;
            end else
                state <= CHECK;
        end
        endcase
    end
end

endmodule

multiplier_datapath.v
module multiplier_datapath(
    input  clk,
    input  reset,
    input  load,
    input  add,
    input  shift,

    input  [31:0] multiplicand,
    input  [31:0] multiplier,

    output [63:0] product,
    output        lsb
);

reg [63:0] product_reg;
reg [63:0] multiplicand_shifted;
reg [31:0] multiplier_reg;

always @(posedge clk or posedge reset) begin
    if (reset) begin
        product_reg <= 64'd0;
        multiplicand_shifted <= 64'd0;
        multiplier_reg <= 32'd0;
    end
    else if (load) begin
        product_reg <= 64'd0;
        multiplicand_shifted <= {32'd0, multiplicand};
        multiplier_reg <= multiplier;
    end
    else begin
        if (add)
            product_reg <= product_reg + multiplicand_shifted;
        if (shift) begin
            multiplicand_shifted <= multiplicand_shifted << 1;
            multiplier_reg <= multiplier_reg >> 1;
        end
    end
end

assign product = product_reg;
assign lsb     = multiplier_reg[0];

endmodule

multiplier32_top.v
/*
Autor: Fabian Chacón 201813154
Tecnológico de Costa Rica
Módulo: multiplier32_top

Descripción:
Módulo top del multiplicador secuencial de 32 bits.

Conecta:
- multiplier_datapath
- multiplier_fsm

Entradas:
clk, reset, start, a, b

Salidas:
result, done
*/

module multiplier32_top(

    input clk,
    input reset,
    input start,

    input [31:0] a,
    input [31:0] b,

    output [63:0] result,
    output done

);

wire load;
wire add;
wire shift;
wire lsb;

multiplier_datapath datapath(

    .clk(clk),
    .reset(reset),

    .load(load),
    .add(add),
    .shift(shift),

    .multiplicand(a),
    .multiplier(b),

    .product(result),
    .lsb(lsb)

);

multiplier_fsm control(

    .clk(clk),
    .reset(reset),
    .start(start),
    .lsb(lsb),

    .load(load),
    .add(add),
    .shift(shift),
    .done(done)

);

endmodule

tb_multiplier.v
`timescale 1ns/1ps

module tb_multiplier;

reg clk;
reg reset;
reg start;

reg [31:0] a;
reg [31:0] b;

wire [63:0] result;
wire done;

multiplier32_top uut(
    .clk(clk),
    .reset(reset),
    .start(start),
    .a(a),
    .b(b),
    .result(result),
    .done(done)
);

always #5 clk = ~clk;

initial begin

    $dumpfile("wave.vcd");
    $dumpvars(0, tb_multiplier);

    clk = 0;
    reset = 1;
    start = 0;

    #10 reset = 0;

    a = 7;
    b = 3;

    start = 1;
    #10 start = 0;

    wait(done);
    $display("7 * 3 = %d", result);

    #20;

    a = 10;
    b = 5;

    start = 1;
    #10 start = 0;

    wait(done);
    $display("10 * 5 = %d", result);

    #20;

    a = 25;
    b = 4;

    start = 1;
    #10 start = 0;

    wait(done);
    $display("25 * 4 = %d", result);

    #50;
    $finish;

end

endmodule

divider_fsm.v
/*
Autor: Fabian Chacón
Módulo: divider_fsm

Descripción:
Máquina de estados para controlar el divisor secuencial de 32 bits.

Controla:
- shift left
- subtract
- restore
- done

Algoritmo:
Repetir 32 veces:
    shift
    subtract
    if negativo -> restore
*/

module divider_fsm(

    input clk,
    input reset,
    input start,
    input sign,        // indica si la resta fue negativa

    output reg load,
    output reg shift,
    output reg subtract,
    output reg restore,
    output reg done

);

reg [5:0] count;
reg [1:0] state;

localparam IDLE     = 2'b00;
localparam SHIFT    = 2'b01;
localparam SUBTRACT = 2'b10;
localparam CHECK    = 2'b11;

always @(posedge clk or posedge reset)
begin

    if(reset)
    begin
        state <= IDLE;
        count <= 0;

        load <= 0;
        shift <= 0;
        subtract <= 0;
        restore <= 0;
        done <= 0;
    end

    else begin

        load <= 0;
        shift <= 0;
        subtract <= 0;
        restore <= 0;

        case(state)

        IDLE:
        begin
            done <= 0;

            if(start)
            begin
                load <= 1;
                count <= 0;
                state <= SHIFT;
            end
        end


        SHIFT:
        begin
            shift <= 1;
            state <= SUBTRACT;
        end


        SUBTRACT:
        begin
            subtract <= 1;
            state <= CHECK;
        end


        CHECK:
        begin

            if(sign)
                restore <= 1;

            count <= count + 1;

            if(count == 31)
            begin
                state <= IDLE;
                done <= 1;
            end
            else
                state <= SHIFT;

        end

        endcase

    end

end

endmodule

divider_datapath.v
/*
Autor: Fabian Chacón
Módulo: divider_datapath

Descripción:
Datapath del divisor secuencial de 32 bits (restoring division).

Contiene:
- registro remainder (64 bits)
- divisor
- operación de resta
- corrimiento a la izquierda

Entradas:
clk, reset
shift, subtract, restore

dividend, divisor

Salidas:
quotient
remainder
sign (para saber si la resta fue negativa)
*/

module divider_datapath(

    input clk,
    input reset,

    input load,
    input shift,
    input subtract,
    input restore,

    input [31:0] dividend,
    input [31:0] divisor,

    output [31:0] quotient,
    output [31:0] remainder,
    output sign

);

reg [63:0] rem_reg;
reg [31:0] divisor_reg;


// cargar divisor
always @(posedge clk or posedge reset)
begin
    if(reset)
        divisor_reg <= 0;
    else if(load)
        divisor_reg <= divisor;
end


// registro principal
always @(posedge clk or posedge reset)
begin

    if(reset)
        rem_reg <= 0;

    else if(load)
        rem_reg <= {32'b0, dividend};

    else begin

        if(shift)
            rem_reg <= rem_reg << 1;

        if(subtract)
            rem_reg[63:32] <= rem_reg[63:32] - divisor_reg;

        if(restore)
            rem_reg[63:32] <= rem_reg[63:32] + divisor_reg;

    end

end


assign quotient  = rem_reg[31:0];
assign remainder = rem_reg[63:32];
assign sign = rem_reg[63];   // indica resultado negativo

endmodule

divider32_top.v
/*
Autor: Fabian Chacón
Módulo: divider32_top

Descripción:
Módulo superior del divisor secuencial de 32 bits.

Conecta:
- FSM (control)
- Datapath (registros y operaciones)

Entradas:
clk, reset, start
dividend, divisor

Salidas:
quotient
remainder
done
*/

module divider32_top(

    input clk,
    input reset,
    input start,

    input [31:0] dividend,
    input [31:0] divisor,

    output [31:0] quotient,
    output [31:0] remainder,
    output done

);

wire shift;
wire subtract;
wire restore;
wire load;
wire sign;


// instancia del datapath
divider_datapath datapath(

    .clk(clk),
    .reset(reset),

    .load(load),
    .shift(shift),
    .subtract(subtract),
    .restore(restore),

    .dividend(dividend),
    .divisor(divisor),

    .quotient(quotient),
    .remainder(remainder),
    .sign(sign)

);


// instancia de la FSM
divider_fsm control(

    .clk(clk),
    .reset(reset),
    .start(start),

    .load(load),
    .sign(sign),

    .shift(shift),
    .subtract(subtract),
    .restore(restore),
    .done(done)

);

endmodule

tb_divider.v
/*
Autor: Fabian Chacón 201813154
Tecnológico de Costa Rica
Módulo: tb_divider

Descripción:
Testbench para el divisor secuencial 32 bits (divider32_top).

Configura estímulos, genera reloj, resetea y verifica resultados mediante $display.
*/

`timescale 1ns/1ps

module tb_divider;

reg clk;
reg reset;
reg start;

reg [31:0] dividend;
reg [31:0] divisor;

wire [31:0] quotient;
wire [31:0] remainder;
wire done;

divider32_top uut(
    .clk(clk),
    .reset(reset),
    .start(start),
    .dividend(dividend),
    .divisor(divisor),
    .quotient(quotient),
    .remainder(remainder),
    .done(done)
);

// reloj
always #5 clk = ~clk;

initial begin

    $dumpfile("wave_divider.vcd");
    $dumpvars(0, tb_divider);

    clk = 0;
    reset = 1;
    start = 0;

    #10
    reset = 0;

    // -------- prueba 1 --------
    dividend = 20;
    divisor = 4;

    start = 1;
    #10 start = 0;

    wait(done);
    $display("20 / 4 = %d remainder %d", quotient, remainder);

    #20;

    // -------- prueba 2 --------
    dividend = 25;
    divisor = 5;

    start = 1;
    #10 start = 0;

    wait(done);
    $display("25 / 5 = %d remainder %d", quotient, remainder);

    #20;

    // -------- prueba 3 --------
    dividend = 27;
    divisor = 4;

    start = 1;
    #10 start = 0;

    wait(done);

    $display("27 / 4 = %d remainder %d", quotient, remainder);

    #50;
    $finish;

end

endmodule

wave_divider.vcd
$date
	Fri Mar 13 06:48:49 2026
$end
$version
	Icarus Verilog
$end
$timescale
	1ps
$end
$scope module tb_divider $end
$var wire 32 ! remainder [31:0] $end
$var wire 32 " quotient [31:0] $end
$var wire 1 # done $end
$var reg 1 $ clk $end
$var reg 32 % dividend [31:0] $end
$var reg 32 & divisor [31:0] $end
$var reg 1 ' reset $end
$var reg 1 ( start $end
$scope module uut $end
$var wire 1 $ clk $end
$var wire 32 ) dividend [31:0] $end
$var wire 32 * divisor [31:0] $end
$var wire 1 ' reset $end
$var wire 1 ( start $end
$var wire 1 + subtract $end
$var wire 1 , sign $end
$var wire 1 - shift $end
$var wire 1 . restore $end
$var wire 32 / remainder [31:0] $end
$var wire 32 0 quotient [31:0] $end
$var wire 1 1 load $end
$var wire 1 # done $end
$scope module control $end
$var wire 1 $ clk $end
$var wire 1 ' reset $end
$var wire 1 ( start $end
$var wire 1 , sign $end
$var parameter 2 2 CHECK $end
$var parameter 2 3 IDLE $end
$var parameter 2 4 SHIFT $end
$var parameter 2 5 SUBTRACT $end
$var reg 6 6 count [5:0] $end
$var reg 1 # done $end
$var reg 1 1 load $end
$var reg 1 . restore $end
$var reg 1 - shift $end
$var reg 2 7 state [1:0] $end
$var reg 1 + subtract $end
$upscope $end
$scope module datapath $end
$var wire 1 $ clk $end
$var wire 32 8 dividend [31:0] $end
$var wire 32 9 divisor [31:0] $end
$var wire 1 1 load $end
$var wire 1 ' reset $end
$var wire 1 . restore $end
$var wire 1 - shift $end
$var wire 1 + subtract $end
$var wire 1 , sign $end
$var wire 32 : remainder [31:0] $end
$var wire 32 ; quotient [31:0] $end
$var reg 32 < divisor_reg [31:0] $end
$var reg 64 = rem_reg [63:0] $end
$upscope $end
$upscope $end
$upscope $end
$scope module tb_multiplier $end
$var wire 64 > result [63:0] $end
$var wire 1 ? done $end
$var reg 32 @ a [31:0] $end
$var reg 32 A b [31:0] $end
$var reg 1 B clk $end
$var reg 1 C reset $end
$var reg 1 D start $end
$scope module uut $end
$var wire 32 E a [31:0] $end
$var wire 32 F b [31:0] $end
$var wire 1 B clk $end
$var wire 1 C reset $end
$var wire 1 D start $end
$var wire 1 G shift $end
$var wire 64 H result [63:0] $end
$var wire 1 I lsb $end
$var wire 1 J load $end
$var wire 1 ? done $end
$var wire 1 K add $end
$scope module control $end
$var wire 1 B clk $end
$var wire 1 C reset $end
$var wire 1 D start $end
$var wire 1 I lsb $end
$var parameter 2 L ADD $end
$var parameter 2 M CHECK $end
$var parameter 2 N IDLE $end
$var parameter 2 O SHIFT $end
$var reg 1 K add $end
$var reg 6 P count [5:0] $end
$var reg 1 ? done $end
$var reg 1 J load $end
$var reg 1 G shift $end
$var reg 2 Q state [1:0] $end
$upscope $end
$scope module datapath $end
$var wire 1 K add $end
$var wire 1 B clk $end
$var wire 1 J load $end
$var wire 32 R multiplicand [31:0] $end
$var wire 32 S multiplier [31:0] $end
$var wire 64 T product [63:0] $end
$var wire 1 C reset $end
$var wire 1 G shift $end
$var wire 1 I lsb $end
$var reg 64 U multiplicand_shifted [63:0] $end
$var reg 32 V multiplier_reg [31:0] $end
$var reg 64 W product_reg [63:0] $end
$upscope $end
$upscope $end
$upscope $end
$enddefinitions $end
$comment Show the parameter values. $end
$dumpall
b11 O
b0 N
b1 M
b10 L
b10 5
b1 4
b0 3
b11 2
$end
#0
$dumpvars
b0 W
b0 V
b0 U
b0 T
bx S
bx R
b0 Q
b0 P
0K
0J
0I
b0 H
0G
bx F
bx E
0D
1C
0B
bx A
bx @
0?
b0 >
b0 =
b0 <
b0 ;
b0 :
bx 9
bx 8
b0 7
b0 6
01
b0 0
b0 /
0.
0-
0,
0+
bx *
bx )
0(
1'
bx &
bx %
0$
0#
b0 "
b0 !
$end
#5000
1B
1$
#10000
0B
0$
1D
b11 A
b11 F
b11 S
b111 @
b111 E
b111 R
0C
1(
b100 &
b100 *
b100 9
b10100 %
b10100 )
b10100 8
0'
#15000
b1 Q
1J
b1 7
11
1B
1$
#20000
0B
0$
0D
0(
#25000
1I
b10100 "
b10100 0
b10100 ;
b11 Q
0J
b11 V
b111 U
b10 7
1-
01
b10100 =
b100 <
1B
1$
#30000
0B
0$
#35000
b101000 "
b101000 0
b101000 ;
b1 Q
b1 P
1G
b101000 =
b11 7
1+
0-
1B
1$
#40000
0B
0$
#45000
b11111111111111111111111111111100 !
b11111111111111111111111111111100 /
b11111111111111111111111111111100 :
1,
b10 Q
0G
b1 V
b1110 U
b1 7
b1 6
0+
b1111111111111111111111111111110000000000000000000000000000101000 =
1B
1$
#50000
0B
0$
#55000
b11 Q
1K
b10 7
1-
1B
1$
#60000
0B
0$
#65000
b1010000 "
b1010000 0
b1010000 ;
b11111111111111111111111111111000 !
b11111111111111111111111111111000 /
b11111111111111111111111111111000 :
b1 Q
b10 P
1G
0K
b1110 >
b1110 H
b1110 T
b1110 W
b11 7
1+
0-
b1111111111111111111111111111100000000000000000000000000001010000 =
1B
1$
#70000
0B
0$
#75000
0I
b11111111111111111111111111110100 !
b11111111111111111111111111110100 /
b11111111111111111111111111110100 :
b0 V
b11100 U
b10 Q
0G
b1111111111111111111111111111010000000000000000000000000001010000 =
b1 7
b10 6
1.
0+
1B
1$
#80000
0B
0$
#85000
b11111111111111111111111111111000 !
b11111111111111111111111111111000 /
b11111111111111111111111111111000 :
b11 Q
1K
b10 7
1-
0.
b1111111111111111111111111111100000000000000000000000000001010000 =
1B
1$
#90000
0B
0$
#95000
b10100000 "
b10100000 0
b10100000 ;
b11111111111111111111111111110000 !
b11111111111111111111111111110000 /
b11111111111111111111111111110000 :
b101010 >
b101010 H
b101010 T
b101010 W
b1 Q
b11 P
1G
0K
b1111111111111111111111111111000000000000000000000000000010100000 =
b11 7
1+
0-
1B
1$
#100000
0B
0$
#105000
b11111111111111111111111111101100 !
b11111111111111111111111111101100 /
b11111111111111111111111111101100 :
b11 Q
0G
b111000 U
b1 7
b11 6
1.
0+
b1111111111111111111111111110110000000000000000000000000010100000 =
1B
1$
#110000
0B
0$
#115000
b11111111111111111111111111110000 !
b11111111111111111111111111110000 /
b11111111111111111111111111110000 :
b1 Q
b100 P
1G
b1111111111111111111111111111000000000000000000000000000010100000 =
b10 7
1-
0.
1B
1$
#120000
0B
0$
#125000
b101000000 "
b101000000 0
b101000000 ;
b11111111111111111111111111100000 !
b11111111111111111111111111100000 /
b11111111111111111111111111100000 :
b11 Q
0G
b1110000 U
b11 7
1+
0-
b1111111111111111111111111110000000000000000000000000000101000000 =
1B
1$
#130000
0B
0$
#135000
b11111111111111111111111111011100 !
b11111111111111111111111111011100 /
b11111111111111111111111111011100 :
b1 Q
b101 P
1G
b1111111111111111111111111101110000000000000000000000000101000000 =
b1 7
b100 6
1.
0+
1B
1$
#140000
0B
0$
#145000
b11111111111111111111111111100000 !
b11111111111111111111111111100000 /
b11111111111111111111111111100000 :
b11 Q
0G
b11100000 U
b10 7
1-
0.
b1111111111111111111111111110000000000000000000000000000101000000 =
1B
1$
#150000
0B
0$
#155000
b1010000000 "
b1010000000 0
b1010000000 ;
b11111111111111111111111111000000 !
b11111111111111111111111111000000 /
b11111111111111111111111111000000 :
b1 Q
b110 P
1G
b1111111111111111111111111100000000000000000000000000001010000000 =
b11 7
1+
0-
1B
1$
#160000
0B
0$
#165000
b11111111111111111111111110111100 !
b11111111111111111111111110111100 /
b11111111111111111111111110111100 :
b11 Q
0G
b111000000 U
b1 7
b101 6
1.
0+
b1111111111111111111111111011110000000000000000000000001010000000 =
1B
1$
#170000
0B
0$
#175000
b11111111111111111111111111000000 !
b11111111111111111111111111000000 /
b11111111111111111111111111000000 :
b1 Q
b111 P
1G
b1111111111111111111111111100000000000000000000000000001010000000 =
b10 7
1-
0.
1B
1$
#180000
0B
0$
#185000
b10100000000 "
b10100000000 0
b10100000000 ;
b11111111111111111111111110000000 !
b11111111111111111111111110000000 /
b11111111111111111111111110000000 :
b11 Q
0G
b1110000000 U
b11 7
1+
0-
b1111111111111111111111111000000000000000000000000000010100000000 =
1B
1$
#190000
0B
0$
#195000
b11111111111111111111111101111100 !
b11111111111111111111111101111100 /
b11111111111111111111111101111100 :
b1 Q
b1000 P
1G
b1111111111111111111111110111110000000000000000000000010100000000 =
b1 7
b110 6
1.
0+
1B
1$
#200000
0B
0$
#205000
b11111111111111111111111110000000 !
b11111111111111111111111110000000 /
b11111111111111111111111110000000 :
b11 Q
0G
b11100000000 U
b10 7
1-
0.
b1111111111111111111111111000000000000000000000000000010100000000 =
1B
1$
#210000
0B
0$
#215000
b101000000000 "
b101000000000 0
b101000000000 ;
b11111111111111111111111100000000 !
b11111111111111111111111100000000 /
b11111111111111111111111100000000 :
b1 Q
b1001 P
1G
b1111111111111111111111110000000000000000000000000000101000000000 =
b11 7
1+
0-
1B
1$
#220000
0B
0$
#225000
b11111111111111111111111011111100 !
b11111111111111111111111011111100 /
b11111111111111111111111011111100 :
b11 Q
0G
b111000000000 U
b1 7
b111 6
1.
0+
b1111111111111111111111101111110000000000000000000000101000000000 =
1B
1$
#230000
0B
0$
#235000
b11111111111111111111111100000000 !
b11111111111111111111111100000000 /
b11111111111111111111111100000000 :
b1 Q
b1010 P
1G
b1111111111111111111111110000000000000000000000000000101000000000 =
b10 7
1-
0.
1B
1$
#240000
0B
0$
#245000
b1010000000000 "
b1010000000000 0
b1010000000000 ;
b11111111111111111111111000000000 !
b11111111111111111111111000000000 /
b11111111111111111111111000000000 :
b11 Q
0G
b1110000000000 U
b11 7
1+
0-
b1111111111111111111111100000000000000000000000000001010000000000 =
1B
1$
#250000
0B
0$
#255000
b11111111111111111111110111111100 !
b11111111111111111111110111111100 /
b11111111111111111111110111111100 :
b1 Q
b1011 P
1G
b1111111111111111111111011111110000000000000000000001010000000000 =
b1 7
b1000 6
1.
0+
1B
1$
#260000
0B
0$
#265000
b11111111111111111111111000000000 !
b11111111111111111111111000000000 /
b11111111111111111111111000000000 :
b11 Q
0G
b11100000000000 U
b10 7
1-
0.
b1111111111111111111111100000000000000000000000000001010000000000 =
1B
1$
#270000
0B
0$
#275000
b10100000000000 "
b10100000000000 0
b10100000000000 ;
b11111111111111111111110000000000 !
b11111111111111111111110000000000 /
b11111111111111111111110000000000 :
b1 Q
b1100 P
1G
b1111111111111111111111000000000000000000000000000010100000000000 =
b11 7
1+
0-
1B
1$
#280000
0B
0$
#285000
b11111111111111111111101111111100 !
b11111111111111111111101111111100 /
b11111111111111111111101111111100 :
b11 Q
0G
b111000000000000 U
b1 7
b1001 6
1.
0+
b1111111111111111111110111111110000000000000000000010100000000000 =
1B
1$
#290000
0B
0$
#295000
b11111111111111111111110000000000 !
b11111111111111111111110000000000 /
b11111111111111111111110000000000 :
b1 Q
b1101 P
1G
b1111111111111111111111000000000000000000000000000010100000000000 =
b10 7
1-
0.
1B
1$
#300000
0B
0$
#305000
b101000000000000 "
b101000000000000 0
b101000000000000 ;
b11111111111111111111100000000000 !
b11111111111111111111100000000000 /
b11111111111111111111100000000000 :
b11 Q
0G
b1110000000000000 U
b11 7
1+
0-
b1111111111111111111110000000000000000000000000000101000000000000 =
1B
1$
#310000
0B
0$
#315000
b11111111111111111111011111111100 !
b11111111111111111111011111111100 /
b11111111111111111111011111111100 :
b1 Q
b1110 P
1G
b1111111111111111111101111111110000000000000000000101000000000000 =
b1 7
b1010 6
1.
0+
1B
1$
#320000
0B
0$
#325000
b11111111111111111111100000000000 !
b11111111111111111111100000000000 /
b11111111111111111111100000000000 :
b11 Q
0G
b11100000000000000 U
b10 7
1-
0.
b1111111111111111111110000000000000000000000000000101000000000000 =
1B
1$
#330000
0B
0$
#335000
b1010000000000000 "
b1010000000000000 0
b1010000000000000 ;
b11111111111111111111000000000000 !
b11111111111111111111000000000000 /
b11111111111111111111000000000000 :
b1 Q
b1111 P
1G
b1111111111111111111100000000000000000000000000001010000000000000 =
b11 7
1+
0-
1B
1$
#340000
0B
0$
#345000
b11111111111111111110111111111100 !
b11111111111111111110111111111100 /
b11111111111111111110111111111100 :
b11 Q
0G
b111000000000000000 U
b1 7
b1011 6
1.
0+
b1111111111111111111011111111110000000000000000001010000000000000 =
1B
1$
#350000
0B
0$
#355000
b11111111111111111111000000000000 !
b11111111111111111111000000000000 /
b11111111111111111111000000000000 :
b1 Q
b10000 P
1G
b1111111111111111111100000000000000000000000000001010000000000000 =
b10 7
1-
0.
1B
1$
#360000
0B
0$
#365000
b10100000000000000 "
b10100000000000000 0
b10100000000000000 ;
b11111111111111111110000000000000 !
b11111111111111111110000000000000 /
b11111111111111111110000000000000 :
b11 Q
0G
b1110000000000000000 U
b11 7
1+
0-
b1111111111111111111000000000000000000000000000010100000000000000 =
1B
1$
#370000
0B
0$
#375000
b11111111111111111101111111111100 !
b11111111111111111101111111111100 /
b11111111111111111101111111111100 :
b1 Q
b10001 P
1G
b1111111111111111110111111111110000000000000000010100000000000000 =
b1 7
b1100 6
1.
0+
1B
1$
#380000
0B
0$
#385000
b11111111111111111110000000000000 !
b11111111111111111110000000000000 /
b11111111111111111110000000000000 :
b11 Q
0G
b11100000000000000000 U
b10 7
1-
0.
b1111111111111111111000000000000000000000000000010100000000000000 =
1B
1$
#390000
0B
0$
#395000
b101000000000000000 "
b101000000000000000 0
b101000000000000000 ;
b11111111111111111100000000000000 !
b11111111111111111100000000000000 /
b11111111111111111100000000000000 :
b1 Q
b10010 P
1G
b1111111111111111110000000000000000000000000000101000000000000000 =
b11 7
1+
0-
1B
1$
#400000
0B
0$
#405000
b11111111111111111011111111111100 !
b11111111111111111011111111111100 /
b11111111111111111011111111111100 :
b11 Q
0G
b111000000000000000000 U
b1 7
b1101 6
1.
0+
b1111111111111111101111111111110000000000000000101000000000000000 =
1B
1$
#410000
0B
0$
#415000
b11111111111111111100000000000000 !
b11111111111111111100000000000000 /
b11111111111111111100000000000000 :
b1 Q
b10011 P
1G
b1111111111111111110000000000000000000000000000101000000000000000 =
b10 7
1-
0.
1B
1$
#420000
0B
0$
#425000
b1010000000000000000 "
b1010000000000000000 0
b1010000000000000000 ;
b11111111111111111000000000000000 !
b11111111111111111000000000000000 /
b11111111111111111000000000000000 :
b11 Q
0G
b1110000000000000000000 U
b11 7
1+
0-
b1111111111111111100000000000000000000000000001010000000000000000 =
1B
1$
#430000
0B
0$
#435000
b11111111111111110111111111111100 !
b11111111111111110111111111111100 /
b11111111111111110111111111111100 :
b1 Q
b10100 P
1G
b1111111111111111011111111111110000000000000001010000000000000000 =
b1 7
b1110 6
1.
0+
1B
1$
#440000
0B
0$
#445000
b11111111111111111000000000000000 !
b11111111111111111000000000000000 /
b11111111111111111000000000000000 :
b11 Q
0G
b11100000000000000000000 U
b10 7
1-
0.
b1111111111111111100000000000000000000000000001010000000000000000 =
1B
1$
#450000
0B
0$
#455000
b10100000000000000000 "
b10100000000000000000 0
b10100000000000000000 ;
b11111111111111110000000000000000 !
b11111111111111110000000000000000 /
b11111111111111110000000000000000 :
b1 Q
b10101 P
1G
b1111111111111111000000000000000000000000000010100000000000000000 =
b11 7
1+
0-
1B
1$
#460000
0B
0$
#465000
b11111111111111101111111111111100 !
b11111111111111101111111111111100 /
b11111111111111101111111111111100 :
b11 Q
0G
b111000000000000000000000 U
b1 7
b1111 6
1.
0+
b1111111111111110111111111111110000000000000010100000000000000000 =
1B
1$
#470000
0B
0$
#475000
b11111111111111110000000000000000 !
b11111111111111110000000000000000 /
b11111111111111110000000000000000 :
b1 Q
b10110 P
1G
b1111111111111111000000000000000000000000000010100000000000000000 =
b10 7
1-
0.
1B
1$
#480000
0B
0$
#485000
b101000000000000000000 "
b101000000000000000000 0
b101000000000000000000 ;
b11111111111111100000000000000000 !
b11111111111111100000000000000000 /
b11111111111111100000000000000000 :
b11 Q
0G
b1110000000000000000000000 U
b11 7
1+
0-
b1111111111111110000000000000000000000000000101000000000000000000 =
1B
1$
#490000
0B
0$
#495000
b11111111111111011111111111111100 !
b11111111111111011111111111111100 /
b11111111111111011111111111111100 :
b1 Q
b10111 P
1G
b1111111111111101111111111111110000000000000101000000000000000000 =
b1 7
b10000 6
1.
0+
1B
1$
#500000
0B
0$
#505000
b11111111111111100000000000000000 !
b11111111111111100000000000000000 /
b11111111111111100000000000000000 :
b11 Q
0G
b11100000000000000000000000 U
b10 7
1-
0.
b1111111111111110000000000000000000000000000101000000000000000000 =
1B
1$
#510000
0B
0$
#515000
b1010000000000000000000 "
b1010000000000000000000 0
b1010000000000000000000 ;
b11111111111111000000000000000000 !
b11111111111111000000000000000000 /
b11111111111111000000000000000000 :
b1 Q
b11000 P
1G
b1111111111111100000000000000000000000000001010000000000000000000 =
b11 7
1+
0-
1B
1$
#520000
0B
0$
#525000
b11111111111110111111111111111100 !
b11111111111110111111111111111100 /
b11111111111110111111111111111100 :
b11 Q
0G
b111000000000000000000000000 U
b1 7
b10001 6
1.
0+
b1111111111111011111111111111110000000000001010000000000000000000 =
1B
1$
#530000
0B
0$
#535000
b11111111111111000000000000000000 !
b11111111111111000000000000000000 /
b11111111111111000000000000000000 :
b1 Q
b11001 P
1G
b1111111111111100000000000000000000000000001010000000000000000000 =
b10 7
1-
0.
1B
1$
#540000
0B
0$
#545000
b10100000000000000000000 "
b10100000000000000000000 0
b10100000000000000000000 ;
b11111111111110000000000000000000 !
b11111111111110000000000000000000 /
b11111111111110000000000000000000 :
b11 Q
0G
b1110000000000000000000000000 U
b11 7
1+
0-
b1111111111111000000000000000000000000000010100000000000000000000 =
1B
1$
#550000
0B
0$
#555000
b11111111111101111111111111111100 !
b11111111111101111111111111111100 /
b11111111111101111111111111111100 :
b1 Q
b11010 P
1G
b1111111111110111111111111111110000000000010100000000000000000000 =
b1 7
b10010 6
1.
0+
1B
1$
#560000
0B
0$
#565000
b11111111111110000000000000000000 !
b11111111111110000000000000000000 /
b11111111111110000000000000000000 :
b11 Q
0G
b11100000000000000000000000000 U
b10 7
1-
0.
b1111111111111000000000000000000000000000010100000000000000000000 =
1B
1$
#570000
0B
0$
#575000
b101000000000000000000000 "
b101000000000000000000000 0
b101000000000000000000000 ;
b11111111111100000000000000000000 !
b11111111111100000000000000000000 /
b11111111111100000000000000000000 :
b1 Q
b11011 P
1G
b1111111111110000000000000000000000000000101000000000000000000000 =
b11 7
1+
0-
1B
1$
#580000
0B
0$
#585000
b11111111111011111111111111111100 !
b11111111111011111111111111111100 /
b11111111111011111111111111111100 :
b11 Q
0G
b111000000000000000000000000000 U
b1 7
b10011 6
1.
0+
b1111111111101111111111111111110000000000101000000000000000000000 =
1B
1$
#590000
0B
0$
#595000
b11111111111100000000000000000000 !
b11111111111100000000000000000000 /
b11111111111100000000000000000000 :
b1 Q
b11100 P
1G
b1111111111110000000000000000000000000000101000000000000000000000 =
b10 7
1-
0.
1B
1$
#600000
0B
0$
#605000
b1010000000000000000000000 "
b1010000000000000000000000 0
b1010000000000000000000000 ;
b11111111111000000000000000000000 !
b11111111111000000000000000000000 /
b11111111111000000000000000000000 :
b11 Q
0G
b1110000000000000000000000000000 U
b11 7
1+
0-
b1111111111100000000000000000000000000001010000000000000000000000 =
1B
1$
#610000
0B
0$
#615000
b11111111110111111111111111111100 !
b11111111110111111111111111111100 /
b11111111110111111111111111111100 :
b1 Q
b11101 P
1G
b1111111111011111111111111111110000000001010000000000000000000000 =
b1 7
b10100 6
1.
0+
1B
1$
#620000
0B
0$
#625000
b11111111111000000000000000000000 !
b11111111111000000000000000000000 /
b11111111111000000000000000000000 :
b11 Q
0G
b11100000000000000000000000000000 U
b10 7
1-
0.
b1111111111100000000000000000000000000001010000000000000000000000 =
1B
1$
#630000
0B
0$
#635000
b10100000000000000000000000 "
b10100000000000000000000000 0
b10100000000000000000000000 ;
b11111111110000000000000000000000 !
b11111111110000000000000000000000 /
b11111111110000000000000000000000 :
b1 Q
b11110 P
1G
b1111111111000000000000000000000000000010100000000000000000000000 =
b11 7
1+
0-
1B
1$
#640000
0B
0$
#645000
b11111111101111111111111111111100 !
b11111111101111111111111111111100 /
b11111111101111111111111111111100 :
b11 Q
0G
b111000000000000000000000000000000 U
b1 7
b10101 6
1.
0+
b1111111110111111111111111111110000000010100000000000000000000000 =
1B
1$
#650000
0B
0$
#655000
b11111111110000000000000000000000 !
b11111111110000000000000000000000 /
b11111111110000000000000000000000 :
b1 Q
b11111 P
1G
b1111111111000000000000000000000000000010100000000000000000000000 =
b10 7
1-
0.
1B
1$
#660000
0B
0$
#665000
b101000000000000000000000000 "
b101000000000000000000000000 0
b101000000000000000000000000 ;
b11111111100000000000000000000000 !
b11111111100000000000000000000000 /
b11111111100000000000000000000000 :
b11 Q
0G
b1110000000000000000000000000000000 U
b11 7
1+
0-
b1111111110000000000000000000000000000101000000000000000000000000 =
1B
1$
#670000
0B
0$
#675000
b11111111011111111111111111111100 !
b11111111011111111111111111111100 /
b11111111011111111111111111111100 :
1?
b0 Q
b100000 P
1G
b1111111101111111111111111111110000000101000000000000000000000000 =
b1 7
b10110 6
1.
0+
1B
1$
#680000
0B
0$
