multiplier_fsm.v
module multiplier_fsm(
    input  clk,
    input  reset,
    input  start,
    input  lsb,

    output reg load,
    output reg add,
    output reg shift,
    output reg done
);

reg [5:0] count;
reg [1:0] state;

localparam IDLE  = 2'b00;
localparam CHECK = 2'b01;
localparam ADD   = 2'b10;
localparam SHIFT = 2'b11;

always @(posedge clk or posedge reset) begin
    if (reset) begin
        state <= IDLE;
        count <= 6'd0;
        load  <= 1'b0;
        add   <= 1'b0;
        shift <= 1'b0;
        done  <= 1'b0;
    end else begin
        // limpiar pulsos
        load  <= 1'b0;
        add   <= 1'b0;
        shift <= 1'b0;
        done  <= 1'b0;

        case (state)
        IDLE: begin
            if (start) begin
                load  <= 1'b1;   // carga {A=0, Q=b} y M=a
                count <= 6'd0;
                state <= CHECK;
            end
        end

        CHECK: begin
            if (lsb)
                state <= ADD;    // si Q0=1 → sumar
            else
                state <= SHIFT;  // si Q0=0 → ir directo a shift
        end

        ADD: begin
            add   <= 1'b1;       // A = A + M
            state <= SHIFT;      // luego desplazar
        end

        SHIFT: begin
            shift <= 1'b1;       // {A,Q} >> 1
            count <= count + 1'b1;
            if (count == 6'd31) begin
                state <= IDLE;
                done <= 1'b1;
            end else
                state <= CHECK;
        end
        endcase
    end
end

endmodule

multiplier_datapath.v
module multiplier_datapath(
    input  clk,
    input  reset,
    input  load,
    input  add,
    input  shift,

    input  [31:0] multiplicand,
    input  [31:0] multiplier,

    output [63:0] product,
    output        lsb
);

reg [63:0] product_reg;
reg [63:0] multiplicand_shifted;
reg [31:0] multiplier_reg;

always @(posedge clk or posedge reset) begin
    if (reset) begin
        product_reg <= 64'd0;
        multiplicand_shifted <= 64'd0;
        multiplier_reg <= 32'd0;
    end
    else if (load) begin
        product_reg <= 64'd0;
        multiplicand_shifted <= {32'd0, multiplicand};
        multiplier_reg <= multiplier;
    end
    else begin
        if (add)
            product_reg <= product_reg + multiplicand_shifted;
        if (shift) begin
            multiplicand_shifted <= multiplicand_shifted << 1;
            multiplier_reg <= multiplier_reg >> 1;
        end
    end
end

assign product = product_reg;
assign lsb     = multiplier_reg[0];

endmodule

multiplier32_top.v
/*
Autor: Fabian Chacón 201813154
Tecnológico de Costa Rica
Módulo: multiplier32_top

Descripción:
Módulo top del multiplicador secuencial de 32 bits.

Conecta:
- multiplier_datapath
- multiplier_fsm

Entradas:
clk, reset, start, a, b

Salidas:
result, done
*/

module multiplier32_top(

    input clk,
    input reset,
    input start,

    input [31:0] a,
    input [31:0] b,

    output [63:0] result,
    output done

);

wire load;
wire add;
wire shift;
wire lsb;

multiplier_datapath datapath(

    .clk(clk),
    .reset(reset),

    .load(load),
    .add(add),
    .shift(shift),

    .multiplicand(a),
    .multiplier(b),

    .product(result),
    .lsb(lsb)

);

multiplier_fsm control(

    .clk(clk),
    .reset(reset),
    .start(start),
    .lsb(lsb),

    .load(load),
    .add(add),
    .shift(shift),
    .done(done)

);

endmodule

tb_multiplier.v
`timescale 1ns/1ps

module tb_multiplier;

reg clk;
reg reset;
reg start;

reg [31:0] a;
reg [31:0] b;

wire [63:0] result;
wire done;

multiplier32_top uut(
    .clk(clk),
    .reset(reset),
    .start(start),
    .a(a),
    .b(b),
    .result(result),
    .done(done)
);

always #5 clk = ~clk;

initial begin

    $dumpfile("wave.vcd");
    $dumpvars(0, tb_multiplier);

    clk = 0;
    reset = 1;
    start = 0;

    #10 reset = 0;

    a = 7;
    b = 3;

    start = 1;
    #10 start = 0;

    wait(done);
    $display("7 * 3 = %d", result);

    #20;

    a = 10;
    b = 5;

    start = 1;
    #10 start = 0;

    wait(done);
    $display("10 * 5 = %d", result);

    #20;

    a = 25;
    b = 4;

    start = 1;
    #10 start = 0;

    wait(done);
    $display("25 * 4 = %d", result);

    #50;
    $finish;

end

endmodule

wave.vcd
$date
	Fri Mar 13 06:48:16 2026
$end
$version
	Icarus Verilog
$end
$timescale
	1ps
$end
$scope module tb_multiplier $end
$var wire 64 ! result [63:0] $end
$var wire 1 " done $end
$var reg 32 # a [31:0] $end
$var reg 32 $ b [31:0] $end
$var reg 1 % clk $end
$var reg 1 & reset $end
$var reg 1 ' start $end
$scope module uut $end
$var wire 32 ( a [31:0] $end
$var wire 32 ) b [31:0] $end
$var wire 1 % clk $end
$var wire 1 & reset $end
$var wire 1 ' start $end
$var wire 1 * shift $end
$var wire 64 + result [63:0] $end
$var wire 1 , lsb $end
$var wire 1 - load $end
$var wire 1 " done $end
$var wire 1 . add $end
$scope module control $end
$var wire 1 % clk $end
$var wire 1 & reset $end
$var wire 1 ' start $end
$var wire 1 , lsb $end
$var parameter 2 / ADD $end
$var parameter 2 0 CHECK $end
$var parameter 2 1 IDLE $end
$var parameter 2 2 SHIFT $end
$var reg 1 . add $end
$var reg 6 3 count [5:0] $end
$var reg 1 " done $end
$var reg 1 - load $end
$var reg 1 * shift $end
$var reg 2 4 state [1:0] $end
$upscope $end
$scope module datapath $end
$var wire 1 . add $end
$var wire 1 % clk $end
$var wire 1 - load $end
$var wire 32 5 multiplicand [31:0] $end
$var wire 32 6 multiplier [31:0] $end
$var wire 64 7 product [63:0] $end
$var wire 1 & reset $end
$var wire 1 * shift $end
$var wire 1 , lsb $end
$var reg 64 8 multiplicand_shifted [63:0] $end
$var reg 32 9 multiplier_reg [31:0] $end
$var reg 64 : product_reg [63:0] $end
$upscope $end
$upscope $end
$upscope $end
$enddefinitions $end
$comment Show the parameter values. $end
$dumpall
b11 2
b0 1
b1 0
b10 /
$end
#0
$dumpvars
b0 :
b0 9
b0 8
b0 7
bx 6
bx 5
b0 4
b0 3
0.
0-
0,
b0 +
0*
bx )
bx (
0'
1&
0%
bx $
bx #
0"
b0 !
$end
#5000
1%
#10000
0%
1'
b11 $
b11 )
b11 6
b111 #
b111 (
b111 5
0&
#15000
b1 4
1-
1%
#20000
0%
0'
#25000
1,
b11 4
0-
b11 9
b111 8
1%
#30000
0%
#35000
b1 4
b1 3
1*
1%
#40000
0%
#45000
b10 4
0*
b1 9
b1110 8
1%
#50000
0%
#55000
b11 4
1.
1%
#60000
0%
#65000
b1 4
b10 3
1*
0.
b1110 !
b1110 +
b1110 7
b1110 :
1%
#70000
0%
#75000
0,
b0 9
b11100 8
b10 4
0*
1%
#80000
0%
#85000
b11 4
1.
1%
#90000
0%
#95000
b101010 !
b101010 +
b101010 7
b101010 :
b1 4
b11 3
1*
0.
1%
#100000
0%
#105000
b11 4
0*
b111000 8
1%
#110000
0%
#115000
b1 4
b100 3
1*
1%
#120000
0%
#125000
b11 4
0*
b1110000 8
1%
#130000
0%
#135000
b1 4
b101 3
1*
1%
#140000
0%
#145000
b11 4
0*
b11100000 8
1%
#150000
0%
#155000
b1 4
b110 3
1*
1%
#160000
0%
#165000
b11 4
0*
b111000000 8
1%
#170000
0%
#175000
b1 4
b111 3
1*
1%
#180000
0%
#185000
b11 4
0*
b1110000000 8
1%
#190000
0%
#195000
b1 4
b1000 3
1*
1%
#200000
0%
#205000
b11 4
0*
b11100000000 8
1%
#210000
0%
#215000
b1 4
b1001 3
1*
1%
#220000
0%
#225000
b11 4
0*
b111000000000 8
1%
#230000
0%
#235000
b1 4
b1010 3
1*
1%
#240000
0%
#245000
b11 4
0*
b1110000000000 8
1%
#250000
0%
#255000
b1 4
b1011 3
1*
1%
#260000
0%
#265000
b11 4
0*
b11100000000000 8
1%
#270000
0%
#275000
b1 4
b1100 3
1*
1%
#280000
0%
#285000
b11 4
0*
b111000000000000 8
1%
#290000
0%
#295000
b1 4
b1101 3
1*
1%
#300000
0%
#305000
b11 4
0*
b1110000000000000 8
1%
#310000
0%
#315000
b1 4
b1110 3
1*
1%
#320000
0%
#325000
b11 4
0*
b11100000000000000 8
1%
#330000
0%
#335000
b1 4
b1111 3
1*
1%
#340000
0%
#345000
b11 4
0*
b111000000000000000 8
1%
#350000
0%
#355000
b1 4
b10000 3
1*
1%
#360000
0%
#365000
b11 4
0*
b1110000000000000000 8
1%
#370000
0%
#375000
b1 4
b10001 3
1*
1%
#380000
0%
#385000
b11 4
0*
b11100000000000000000 8
1%
#390000
0%
#395000
b1 4
b10010 3
1*
1%
#400000
0%
#405000
b11 4
0*
b111000000000000000000 8
1%
#410000
0%
#415000
b1 4
b10011 3
1*
1%
#420000
0%
#425000
b11 4
0*
b1110000000000000000000 8
1%
#430000
0%
#435000
b1 4
b10100 3
1*
1%
#440000
0%
#445000
b11 4
0*
b11100000000000000000000 8
1%
#450000
0%
#455000
b1 4
b10101 3
1*
1%
#460000
0%
#465000
b11 4
0*
b111000000000000000000000 8
1%
#470000
0%
#475000
b1 4
b10110 3
1*
1%
#480000
0%
#485000
b11 4
0*
b1110000000000000000000000 8
1%
#490000
0%
#495000
b1 4
b10111 3
1*
1%
#500000
0%
#505000
b11 4
0*
b11100000000000000000000000 8
1%
#510000
0%
#515000
b1 4
b11000 3
1*
1%
#520000
0%
#525000
b11 4
0*
b111000000000000000000000000 8
1%
#530000
0%
#535000
b1 4
b11001 3
1*
1%
#540000
0%
#545000
b11 4
0*
b1110000000000000000000000000 8
1%
#550000
0%
#555000
b1 4
b11010 3
1*
1%
#560000
0%
#565000
b11 4
0*
b11100000000000000000000000000 8
1%
#570000
0%
#575000
b1 4
b11011 3
1*
1%
#580000
0%
#585000
b11 4
0*
b111000000000000000000000000000 8
1%
#590000
0%
#595000
b1 4
b11100 3
1*
1%
#600000
0%
#605000
b11 4
0*
b1110000000000000000000000000000 8
1%
#610000
0%
#615000
b1 4
b11101 3
1*
1%
#620000
0%
#625000
b11 4
0*
b11100000000000000000000000000000 8
1%
#630000
0%
#635000
b1 4
b11110 3
1*
1%
#640000
0%
#645000
b11 4
0*
b111000000000000000000000000000000 8
1%
#650000
0%
#655000
b1 4
b11111 3
1*
1%
#660000
0%
#665000
b11 4
0*
b1110000000000000000000000000000000 8
1%
#670000
0%
#675000
1"
b0 4
b100000 3
1*
1%
#680000
0%
#685000
0"
0*
b11100000000000000000000000000000000 8
1%
#690000
0%
#695000
b1 4
b0 3
1-
1%
1'
b101 $
b101 )
b101 6
b1010 #
b1010 (
b1010 5
#700000
0%
#705000
1,
b11 4
0-
b101 9
b1010 8
b0 !
b0 +
b0 7
b0 :
1%
0'
#710000
0%
#715000
b1 4
b1 3
1*
1%
#720000
0%
#725000
0,
b10 4
0*
b10 9
b10100 8
1%
#730000
0%
#735000
b11 4
1.
1%
#740000
0%
#745000
b1 4
b10 3
1*
0.
b10100 !
b10100 +
b10100 7
b10100 :
1%
#750000
0%
#755000
1,
b1 9
b101000 8
b11 4
0*
1%
#760000
0%
#765000
b1 4
b11 3
1*
1%
#770000
0%
#775000
0,
b0 9
b1010000 8
b10 4
0*
1%
#780000
0%
#785000
b11 4
1.
1%
#790000
0%
#795000
b1100100 !
b1100100 +
b1100100 7
b1100100 :
b1 4
b100 3
1*
0.
1%
#800000
0%
#805000
b11 4
0*
b10100000 8
1%
#810000
0%
#815000
b1 4
b101 3
1*
1%
#820000
0%
#825000
b11 4
0*
b101000000 8
1%
#830000
0%
#835000
b1 4
b110 3
1*
1%
#840000
0%
#845000
b11 4
0*
b1010000000 8
1%
#850000
0%
#855000
b1 4
b111 3
1*
1%
#860000
0%
#865000
b11 4
0*
b10100000000 8
1%
#870000
0%
#875000
b1 4
b1000 3
1*
1%
#880000
0%
#885000
b11 4
0*
b101000000000 8
1%
#890000
0%
#895000
b1 4
b1001 3
1*
1%
#900000
0%
#905000
b11 4
0*
b1010000000000 8
1%
#910000
0%
#915000
b1 4
b1010 3
1*
1%
#920000
0%
#925000
b11 4
0*
b10100000000000 8
1%
#930000
0%
#935000
b1 4
b1011 3
1*
1%
#940000
0%
#945000
b11 4
0*
b101000000000000 8
1%
#950000
0%
#955000
b1 4
b1100 3
1*
1%
#960000
0%
#965000
b11 4
0*
b1010000000000000 8
1%
#970000
0%
#975000
b1 4
b1101 3
1*
1%
#980000
0%
#985000
b11 4
0*
b10100000000000000 8
1%
#990000
0%
#995000
b1 4
b1110 3
1*
1%
#1000000
0%
#1005000
b11 4
0*
b101000000000000000 8
1%
#1010000
0%
#1015000
b1 4
b1111 3
1*
1%
#1020000
0%
#1025000
b11 4
0*
b1010000000000000000 8
1%
#1030000
0%
#1035000
b1 4
b10000 3
1*
1%
#1040000
0%
#1045000
b11 4
0*
b10100000000000000000 8
1%
#1050000
0%
#1055000
b1 4
b10001 3
1*
1%
#1060000
0%
#1065000
b11 4
0*
b101000000000000000000 8
1%
#1070000
0%
#1075000
b1 4
b10010 3
1*
1%
#1080000
0%
#1085000
b11 4
0*
b1010000000000000000000 8
1%
#1090000
0%
#1095000
b1 4
b10011 3
1*
1%
#1100000
0%
#1105000
b11 4
0*
b10100000000000000000000 8
1%
#1110000
0%
#1115000
b1 4
b10100 3
1*
1%
#1120000
0%
#1125000
b11 4
0*
b101000000000000000000000 8
1%
#1130000
0%
#1135000
b1 4
b10101 3
1*
1%
#1140000
0%
#1145000
b11 4
0*
b1010000000000000000000000 8
1%
#1150000
0%
#1155000
b1 4
b10110 3
1*
1%
#1160000
0%
#1165000
b11 4
0*
b10100000000000000000000000 8
1%
#1170000
0%
#1175000
b1 4
b10111 3
1*
1%
#1180000
0%
#1185000
b11 4
0*
b101000000000000000000000000 8
1%
#1190000
0%
#1195000
b1 4
b11000 3
1*
1%
#1200000
0%
#1205000
b11 4
0*
b1010000000000000000000000000 8
1%
#1210000
0%
#1215000
b1 4
b11001 3
1*
1%
#1220000
0%
#1225000
b11 4
0*
b10100000000000000000000000000 8
1%
#1230000
0%
#1235000
b1 4
b11010 3
1*
1%
#1240000
0%
#1245000
b11 4
0*
b101000000000000000000000000000 8
1%
#1250000
0%
#1255000
b1 4
b11011 3
1*
1%
#1260000
0%
#1265000
b11 4
0*
b1010000000000000000000000000000 8
1%
#1270000
0%
#1275000
b1 4
b11100 3
1*
1%
#1280000
0%
#1285000
b11 4
0*
b10100000000000000000000000000000 8
1%
#1290000
0%
#1295000
b1 4
b11101 3
1*
1%
#1300000
0%
#1305000
b11 4
0*
b101000000000000000000000000000000 8
1%
#1310000
0%
#1315000
b1 4
b11110 3
1*
1%
#1320000
0%
#1325000
b11 4
0*
b1010000000000000000000000000000000 8
1%
#1330000
0%
#1335000
b1 4
b11111 3
1*
1%
#1340000
0%
#1345000
b11 4
0*
b10100000000000000000000000000000000 8
1%
#1350000
0%
#1355000
1"
b0 4
b100000 3
1*
1%
#1360000
0%
#1365000
0"
0*
b101000000000000000000000000000000000 8
1%
#1370000
0%
#1375000
b1 4
b0 3
1-
1%
1'
b100 $
b100 )
b100 6
b11001 #
b11001 (
b11001 5
#1380000
0%
#1385000
b11 4
0-
b100 9
b11001 8
b0 !
b0 +
b0 7
b0 :
1%
0'
#1390000
0%
#1395000
b1 4
b1 3
1*
1%
#1400000
0%
#1405000
b11 4
0*
b10 9
b110010 8
1%
#1410000
0%
#1415000
b1 4
b10 3
1*
1%
#1420000
0%
#1425000
1,
b11 4
0*
b1 9
b1100100 8
1%
#1430000
0%
#1435000
b1 4
b11 3
1*
1%
#1440000
0%
#1445000
0,
b10 4
0*
b0 9
b11001000 8
1%
#1450000
0%
#1455000
b11 4
1.
1%
#1460000
0%
#1465000
b1 4
b100 3
1*
0.
b11001000 !
b11001000 +
b11001000 7
b11001000 :
1%
#1470000
0%
#1475000
b110010000 8
b11 4
0*
1%
#1480000
0%
#1485000
b1 4
b101 3
1*
1%
#1490000
0%
#1495000
b1100100000 8
b11 4
0*
1%
#1500000
0%
#1505000
b1 4
b110 3
1*
1%
#1510000
0%
#1515000
b11001000000 8
b11 4
0*
1%
#1520000
0%
#1525000
b1 4
b111 3
1*
1%
#1530000
0%
#1535000
b110010000000 8
b11 4
0*
1%
#1540000
0%
#1545000
b1 4
b1000 3
1*
1%
#1550000
0%
#1555000
b1100100000000 8
b11 4
0*
1%
#1560000
0%
#1565000
b1 4
b1001 3
1*
1%
#1570000
0%
#1575000
b11001000000000 8
b11 4
0*
1%
#1580000
0%
#1585000
b1 4
b1010 3
1*
1%
#1590000
0%
#1595000
b110010000000000 8
b11 4
0*
1%
#1600000
0%
#1605000
b1 4
b1011 3
1*
1%
#1610000
0%
#1615000
b1100100000000000 8
b11 4
0*
1%
#1620000
0%
#1625000
b1 4
b1100 3
1*
1%
#1630000
0%
#1635000
b11001000000000000 8
b11 4
0*
1%
#1640000
0%
#1645000
b1 4
b1101 3
1*
1%
#1650000
0%
#1655000
b110010000000000000 8
b11 4
0*
1%
#1660000
0%
#1665000
b1 4
b1110 3
1*
1%
#1670000
0%
#1675000
b1100100000000000000 8
b11 4
0*
1%
#1680000
0%
#1685000
b1 4
b1111 3
1*
1%
#1690000
0%
#1695000
b11001000000000000000 8
b11 4
0*
1%
#1700000
0%
#1705000
b1 4
b10000 3
1*
1%
#1710000
0%
#1715000
b110010000000000000000 8
b11 4
0*
1%
#1720000
0%
#1725000
b1 4
b10001 3
1*
1%
#1730000
0%
#1735000
b1100100000000000000000 8
b11 4
0*
1%
#1740000
0%
#1745000
b1 4
b10010 3
1*
1%
#1750000
0%
#1755000
b11001000000000000000000 8
b11 4
0*
1%
#1760000
0%
#1765000
b1 4
b10011 3
1*
1%
#1770000
0%
#1775000
b110010000000000000000000 8
b11 4
0*
1%
#1780000
0%
#1785000
b1 4
b10100 3
1*
1%
#1790000
0%
#1795000
b1100100000000000000000000 8
b11 4
0*
1%
#1800000
0%
#1805000
b1 4
b10101 3
1*
1%
#1810000
0%
#1815000
b11001000000000000000000000 8
b11 4
0*
1%
#1820000
0%
#1825000
b1 4
b10110 3
1*
1%
#1830000
0%
#1835000
b110010000000000000000000000 8
b11 4
0*
1%
#1840000
0%
#1845000
b1 4
b10111 3
1*
1%
#1850000
0%
#1855000
b1100100000000000000000000000 8
b11 4
0*
1%
#1860000
0%
#1865000
b1 4
b11000 3
1*
1%
#1870000
0%
#1875000
b11001000000000000000000000000 8
b11 4
0*
1%
#1880000
0%
#1885000
b1 4
b11001 3
1*
1%
#1890000
0%
#1895000
b110010000000000000000000000000 8
b11 4
0*
1%
#1900000
0%
#1905000
b1 4
b11010 3
1*
1%
#1910000
0%
#1915000
b1100100000000000000000000000000 8
b11 4
0*
1%
#1920000
0%
#1925000
b1 4
b11011 3
1*
1%
#1930000
0%
#1935000
b11001000000000000000000000000000 8
b11 4
0*
1%
#1940000
0%
#1945000
b1 4
b11100 3
1*
1%
#1950000
0%
#1955000
b110010000000000000000000000000000 8
b11 4
0*
1%
#1960000
0%
#1965000
b1 4
b11101 3
1*
1%
#1970000
0%
#1975000
b1100100000000000000000000000000000 8
b11 4
0*
1%
#1980000
0%
#1985000
b1 4
b11110 3
1*
1%
#1990000
0%
#1995000
b11001000000000000000000000000000000 8
b11 4
0*
1%
#2000000
0%
#2005000
b1 4
b11111 3
1*
1%
#2010000
0%
#2015000
b110010000000000000000000000000000000 8
b11 4
0*
1%
#2020000
0%
#2025000
1"
b0 4
b100000 3
1*
1%
#2030000
0%
#2035000
b1100100000000000000000000000000000000 8
0"
0*
1%
