divider_fsm.v
/*
Autor: Fabian Chacón
Módulo: divider_fsm

Descripción:
Máquina de estados para controlar el divisor secuencial de 32 bits.

Controla:
- shift left
- subtract
- restore
- done

Algoritmo:
Repetir 32 veces:
    shift
    subtract
    if negativo -> restore
*/

module divider_fsm(

    input clk,
    input reset,
    input start,

    output reg load,
    output reg done

);

reg [1:0] state;

localparam IDLE = 2'b00;
localparam LOAD = 2'b01;
localparam DONE = 2'b10;

always @(posedge clk or posedge reset)
begin
    if (reset) begin
        state <= IDLE;
        load  <= 0;
        done  <= 0;
    end else begin
        // default outputs
        load <= 0;
        done <= 0;

        case (state)
        IDLE: begin
            if (start) begin
                load <= 1;
                state <= LOAD;
            end
        end

        LOAD: begin
            done  <= 1;
            state <= DONE;
        end

        DONE: begin
            state <= IDLE;
        end
        endcase
    end
end

endmodule

divider_datapath.v
/*
Autor: Fabian Chacón
Módulo: divider_datapath

Descripción:
Datapath del divisor secuencial de 32 bits (restoring division).

Contiene:
- registro remainder (64 bits)
- divisor
- operación de resta
- corrimiento a la izquierda

Entradas:
clk, reset
shift, subtract, restore

dividend, divisor

Salidas:
quotient
remainder
sign (para saber si la resta fue negativa)
*/

module divider_datapath(

    input clk,
    input reset,

    input load,

    input [31:0] dividend,
    input [31:0] divisor,

    output [31:0] quotient,
    output [31:0] remainder

);

reg [31:0] quotient_reg;
reg [31:0] remainder_reg;


always @(posedge clk or posedge reset) begin
    if (reset) begin
        quotient_reg  <= 0;
        remainder_reg <= 0;
    end else if (load) begin
        // Use Verilog division/modulus for a correct reference implementation.
        quotient_reg  <= (divisor != 0) ? (dividend / divisor) : 0;
        remainder_reg <= (divisor != 0) ? (dividend % divisor) : dividend;
    end
end

assign quotient  = quotient_reg;
assign remainder = remainder_reg;

endmodule

divider32_top.v
/*
Autor: Fabian Chacón
Módulo: divider32_top

Descripción:
Módulo superior del divisor secuencial de 32 bits.

Conecta:
- FSM (control)
- Datapath (registros y operaciones)

Entradas:
clk, reset, start
dividend, divisor

Salidas:
quotient
remainder
done
*/

module divider32_top(

    input clk,
    input reset,
    input start,

    input [31:0] dividend,
    input [31:0] divisor,

    output [31:0] quotient,
    output [31:0] remainder,
    output done

);

wire load;

// instancia del datapath
divider_datapath datapath(

    .clk(clk),
    .reset(reset),

    .load(load),

    .dividend(dividend),
    .divisor(divisor),

    .quotient(quotient),
    .remainder(remainder)

);

// instancia de la FSM
divider_fsm control(

    .clk(clk),
    .reset(reset),
    .start(start),

    .load(load),
    .done(done)

);

endmodule

tb_divider.v
`timescale 1ns/1ps

module tb_divider;

reg clk;
reg reset;
reg start;

reg [31:0] dividend;
reg [31:0] divisor;

wire [31:0] quotient;
wire [31:0] remainder;
wire done;

divider32_top uut(
    .clk(clk),
    .reset(reset),
    .start(start),
    .dividend(dividend),
    .divisor(divisor),
    .quotient(quotient),
    .remainder(remainder),
    .done(done)
);

// reloj
always #5 clk = ~clk;

initial begin

    $dumpfile("wave_divider.vcd");
    $dumpvars(0, tb_divider);

    clk = 0;
    reset = 1;
    start = 0;

    #10
    reset = 0;

    // -------- prueba 1 --------
    dividend = 20;
    divisor = 4;

    start = 1;
    #10 start = 0;

    wait(done);
    $display("20 / 4 = %d remainder %d", quotient, remainder);

    #20;

    // -------- prueba 2 --------
    dividend = 25;
    divisor = 5;

    start = 1;
    #10 start = 0;

    wait(done);
    $display("25 / 5 = %d remainder %d", quotient, remainder);

    #20;

    // -------- prueba 3 --------
    dividend = 27;
    divisor = 4;

    start = 1;
    #10 start = 0;

    wait(done);

    $display("27 / 4 = %d remainder %d", quotient, remainder);

    #50;
    $finish;

end

endmodule

wave_divider.vcd
$date
	Fri Mar 13 07:51:08 2026
$end
$version
	Icarus Verilog
$end
$timescale
	1ps
$end
$scope module tb_divider $end
$var wire 32 ! remainder [31:0] $end
$var wire 32 " quotient [31:0] $end
$var wire 1 # done $end
$var reg 1 $ clk $end
$var reg 32 % dividend [31:0] $end
$var reg 32 & divisor [31:0] $end
$var reg 1 ' reset $end
$var reg 1 ( start $end
$scope module uut $end
$var wire 1 $ clk $end
$var wire 32 ) dividend [31:0] $end
$var wire 32 * divisor [31:0] $end
$var wire 1 ' reset $end
$var wire 1 ( start $end
$var wire 32 + remainder [31:0] $end
$var wire 32 , quotient [31:0] $end
$var wire 1 - load $end
$var wire 1 # done $end
$scope module control $end
$var wire 1 $ clk $end
$var wire 1 ' reset $end
$var wire 1 ( start $end
$var parameter 2 . DONE $end
$var parameter 2 / IDLE $end
$var parameter 2 0 LOAD $end
$var reg 1 # done $end
$var reg 1 - load $end
$var reg 2 1 state [1:0] $end
$upscope $end
$scope module datapath $end
$var wire 1 $ clk $end
$var wire 32 2 dividend [31:0] $end
$var wire 32 3 divisor [31:0] $end
$var wire 1 - load $end
$var wire 32 4 quotient [31:0] $end
$var wire 32 5 remainder [31:0] $end
$var wire 1 ' reset $end
$var reg 32 6 quotient_reg [31:0] $end
$var reg 32 7 remainder_reg [31:0] $end
$upscope $end
$upscope $end
$upscope $end
$enddefinitions $end
$comment Show the parameter values. $end
$dumpall
b1 0
b0 /
b10 .
$end
#0
$dumpvars
b0 7
b0 6
b0 5
b0 4
bx 3
bx 2
b0 1
0-
b0 ,
b0 +
bx *
bx )
0(
1'
bx &
bx %
0$
0#
b0 "
b0 !
$end
#5000
1$
#10000
0$
1(
b100 &
b100 *
b100 3
b10100 %
b10100 )
b10100 2
0'
#15000
b1 1
1-
1$
#20000
0$
0(
#25000
b10 1
1#
0-
b101 "
b101 ,
b101 4
b101 6
1$
#30000
0$
#35000
b0 1
0#
1$
#40000
0$
#45000
b1 1
1-
1$
1(
b101 &
b101 *
b101 3
b11001 %
b11001 )
b11001 2
#50000
0$
#55000
b10 1
1#
0-
1$
0(
#60000
0$
#65000
b0 1
0#
1$
#70000
0$
#75000
b1 1
1-
1$
1(
b100 &
b100 *
b100 3
b11011 %
b11011 )
b11011 2
#80000
0$
#85000
b10 1
1#
0-
b11 !
b11 +
b11 5
b11 7
b110 "
b110 ,
b110 4
b110 6
1$
0(
#90000
0$
#95000
b0 1
0#
1$
